gptscriptlang/cli.py
gptscriptlang-0.1.8.dist-info/METADATA
gptscriptlang-0.1.8.dist-info/WHEEL
gptscriptlang-0.1.8.dist-info/entry_points.txt
gptscriptlang-0.1.8.dist-info/top_level.txt
gptscriptlang-0.1.8.dist-info/RECORD
