Metadata-Version: 2.4
Name: GPTScriptLang
Version: 0.1.8
Summary: GPTScript - The LLM scripting language
License: MIT
Project-URL: Documentation, https://gptscript.readthedocs.io/en/latest/
Requires-Python: >=3.7
Requires-Dist: requests
